brainbite/__init__.py
brainbite/__main__.py
brainbite/biter/__init__.py
brainbite/biter/biter.py
brainbite/biter/data_model.py
brainbite/sample/fizzbuzz.bf
brainbite/sample/fizzbuzz_oneline.bf
brainbite/sample/hello_world.bf
brainbite/sample/print_prime_numbers.bf
brainbite/transpiler/__init__.py
brainbite/transpiler/code_skeleton.json
brainbite/transpiler/substitute.json
brainbite/transpiler/transpiler.py
brainbite-1.0.2.dist-info/LICENSE
brainbite-1.0.2.dist-info/METADATA
brainbite-1.0.2.dist-info/WHEEL
brainbite-1.0.2.dist-info/top_level.txt
brainbite-1.0.2.dist-info/RECORD
