Metadata-Version: 2.1
Name: brainbite
Version: 1.0.2
Summary: A python bit my brain.
Home-page: https://github.com/LouiS0616/brainbite
Author: LouiSakaki
Author-email: e1352207@outlook.jp
License: MIT
Platform: UNKNOWN
Requires-Python: >=3.6
